AUTHORS.rst
CONTRIBUTING.rst
HISTORY.rst
LICENSE
MANIFEST.in
README.rst
setup.cfg
setup.py
docs/Makefile
docs/authors.rst
docs/conf.py
docs/contributing.rst
docs/featurevectormatrix.rst
docs/history.rst
docs/index.rst
docs/installation.rst
docs/make.bat
docs/modules.rst
docs/readme.rst
docs/usage.rst
featurevectormatrix/__init__.py
featurevectormatrix/featurevectormatrix.py
featurevectormatrix.egg-info/PKG-INFO
featurevectormatrix.egg-info/SOURCES.txt
featurevectormatrix.egg-info/dependency_links.txt
featurevectormatrix.egg-info/not-zip-safe
featurevectormatrix.egg-info/top_level.txt
tests/__init__.py
tests/test_featurevectormatrix.py