Metadata-Version: 1.1
Name: featurevectormatrix
Version: 0.1.1
Summary: Python class to encapsulate different representations of large datasets
Home-page: https://github.com/talentpair/featurevectormatrix
Author: Jeremy Robin
Author-email: jeremy.robin@gmail.com
License: BSD
Keywords: featurevectormatrix
Platform: UNKNOWN
Classifier: Development Status :: 2 - Pre-Alpha
Classifier: Intended Audience :: Developers
Classifier: License :: OSI Approved :: BSD License
Classifier: Natural Language :: English
Classifier: Programming Language :: Python :: 2
Classifier: Programming Language :: Python :: 2.7
